nexgraphpy/__init__.py
nexgraphpy/nexgraph.py
nexgraphpy-2.1.0.dist-info/METADATA
nexgraphpy-2.1.0.dist-info/WHEEL
nexgraphpy-2.1.0.dist-info/licenses/LICENSE
nexgraphpy-2.1.0.dist-info/RECORD
