Metadata-Version: 2.4
Name: nexgraphpy
Version: 2.1.0
Summary: Python library for connecting with Nextech force gauges over USB Serial
Project-URL: Homepage, https://github.com/simply-shawn/nexgraphpy
Project-URL: Documentation, https://python.nexgraphapp.com/
Project-URL: Source, https://github.com/simply-shawn/nexgraphpy
Project-URL: Bug Tracker, https://github.com/simply-shawn/nexgraphpy/issues
Project-URL: Changelog, https://github.com/simply-shawn/nexgraphpy/blob/main/CHANGES.md
Author-email: Shawn Myratchapon <info@nexgraphapp.com>
License-Expression: GPL-3.0-only WITH Classpath-exception-2.0 OR BSD-3-Clause
License-File: LICENSE
Keywords: force,gauge,nexgraph,nextech,torque
Classifier: Development Status :: 5 - Production/Stable
Classifier: Programming Language :: Python :: 3.10
Classifier: Programming Language :: Python :: 3.11
Classifier: Programming Language :: Python :: 3.12
Classifier: Programming Language :: Python :: 3.13
Requires-Python: >=3.10
Requires-Dist: matplotlib
Requires-Dist: numpy
Requires-Dist: pyserial
